sequel/__init__.py
sequel/algos/__init__.py
sequel/algos/base_algo.py
sequel/algos/jax/__init__.py
sequel/algos/jax/agem.py
sequel/algos/jax/der.py
sequel/algos/jax/er.py
sequel/algos/jax/ewc.py
sequel/algos/jax/jax_base_algo.py
sequel/algos/jax/joint.py
sequel/algos/jax/lfl.py
sequel/algos/jax/mas.py
sequel/algos/jax/mcsgd.py
sequel/algos/jax/si.py
sequel/algos/pytorch/__init__.py
sequel/algos/pytorch/agem.py
sequel/algos/pytorch/der.py
sequel/algos/pytorch/er.py
sequel/algos/pytorch/ewc.py
sequel/algos/pytorch/icarl.py
sequel/algos/pytorch/joint.py
sequel/algos/pytorch/kcl.py
sequel/algos/pytorch/lamaml.py
sequel/algos/pytorch/lfl.py
sequel/algos/pytorch/mas.py
sequel/algos/pytorch/mcsgd.py
sequel/algos/pytorch/pytorch_base_algo.py
sequel/algos/pytorch/si.py
sequel/algos/pytorch/utils/__init__.py
sequel/algos/pytorch/utils/weight_gradient_manipulation.py
sequel/algos/utils/__init__.py
sequel/algos/utils/callback_hooks.py
sequel/algos/utils/state_manager.py
sequel/backbones/__init__.py
sequel/backbones/jax/__init__.py
sequel/backbones/jax/base_backbone.py
sequel/backbones/jax/cnn.py
sequel/backbones/jax/mlp.py
sequel/backbones/jax/resnet.py
sequel/backbones/jax/utils.py
sequel/backbones/pytorch/__init__.py
sequel/backbones/pytorch/base_backbone.py
sequel/backbones/pytorch/cnn.py
sequel/backbones/pytorch/mlp.py
sequel/backbones/pytorch/resnet.py
sequel/backbones/pytorch/utils.py
sequel/backbones/pytorch/model_factory/__init__.py
sequel/backbones/pytorch/model_factory/kcl.py
sequel/benchmarks/__init__.py
sequel/benchmarks/base_benchmark.py
sequel/benchmarks/buffer.py
sequel/benchmarks/cifar.py
sequel/benchmarks/memory.py
sequel/benchmarks/mnist.py
sequel/benchmarks/tinyimagenet.py
sequel/benchmarks/utils.py
sequel/utils/__init__.py
sequel/utils/utils.py
sequel/utils/callbacks/__init__.py
sequel/utils/callbacks/algo_callback.py
sequel/utils/callbacks/base_callback.py
sequel/utils/callbacks/dummy.py
sequel/utils/callbacks/input_visualization_callback.py
sequel_core-0.0.2.dist-info/LICENSE
sequel_core-0.0.2.dist-info/METADATA
sequel_core-0.0.2.dist-info/WHEEL
sequel_core-0.0.2.dist-info/top_level.txt
sequel_core-0.0.2.dist-info/RECORD
