Metadata-Version: 2.1
Name: sequel-core
Version: 0.0.2
Summary: A Continual Learning Framework for both Jax and PyTorch.
Author-email: Nikolaos Dimitriadis <nikolaos.dimitriadis@epfl.ch>
Project-URL: repository, https://github.com/nik-dim/sequel
Project-URL: homepage, https://nik-dim.github.io/sequel-site/
Project-URL: documentation, https://nik-dim.github.io/sequel-site/
Project-URL: issue-tracker, https://github.com/nik-dim/sequel/issues
Project-URL: releases, https://github.com/nik-dim/sequel/releases
Keywords: continual learning,pytorch,jax
Classifier: Development Status :: 3 - Alpha
Classifier: Programming Language :: Python :: 3
Classifier: License :: OSI Approved :: MIT License
Classifier: Operating System :: OS Independent
Requires-Python: >=3.10
License-File: LICENSE
Requires-Dist: beautifultable (==1.1.0)
Requires-Dist: coloredlogs (==15.0.1)
Requires-Dist: comet-ml (==3.31.21)
Requires-Dist: functorch (==1.13.1)
Requires-Dist: hydra-core (==1.3.2)
Requires-Dist: matplotlib (==3.6.2)
Requires-Dist: numpy (==1.23.4)
Requires-Dist: omegaconf (==2.2.3)
Requires-Dist: pandas (==1.5.1)
Requires-Dist: Pillow (==9.4.0)
Requires-Dist: pytest (==7.2.1)
Requires-Dist: torch (==1.13.1)
Requires-Dist: torchmetrics (==0.10.3)
Requires-Dist: torchvision (==0.14.1)
Requires-Dist: tqdm (==4.64.1)
Requires-Dist: wandb (==0.13.11)
Requires-Dist: tensorboard (==2.12.0)
Requires-Dist: gpustat (==1.0.0)
Requires-Dist: mkdocs (==1.4.2)
Requires-Dist: mkdocs-material (==9.1.2)
Requires-Dist: mkdocstrings (==0.20.0)
Requires-Dist: mkdocstrings-python (==0.8.3)
Requires-Dist: jax
Requires-Dist: chex (==0.1.5)
Requires-Dist: flax (==0.6.7)
Requires-Dist: optax (==0.1.4)
Requires-Dist: jax-resnet (==0.0.4)
